openai_func_call/__init__.py
openai_func_call/assembly.py
openai_func_call/function_parsing.py
openai_func_call/manager.py
openai_func_call/schemas.py
openai_func_call-0.1.0.dist-info/METADATA
openai_func_call-0.1.0.dist-info/WHEEL
openai_func_call-0.1.0.dist-info/RECORD
